vagrant_metadata.py
vagrant_metadata-1.1.2.data/scripts/vagrant-metadata
vagrant_metadata-1.1.2.dist-info/LICENSE
vagrant_metadata-1.1.2.dist-info/METADATA
vagrant_metadata-1.1.2.dist-info/WHEEL
vagrant_metadata-1.1.2.dist-info/top_level.txt
vagrant_metadata-1.1.2.dist-info/RECORD
