Metadata-Version: 2.1
Name: vagrant-metadata
Version: 1.1.2
Summary: Vagrant metadata.json generator
Home-page: https://github.com/lvillani/vagrant-metadata/
Author: Lorenzo Villani
Author-email: lorenzo@villani.me
License: UNKNOWN
Platform: UNKNOWN
Classifier: Development Status :: 5 - Production/Stable
Classifier: Intended Audience :: Developers
Classifier: License :: OSI Approved :: MIT License
